mojo_arrow_sys.cpython-312-darwin.so
mojo_arrow_sys-0.1.20.dist-info/RECORD
mojo_arrow_sys-0.1.20.dist-info/WHEEL
mojo_arrow_sys-0.1.20.dist-info/top_level.txt
mojo_arrow_sys-0.1.20.dist-info/METADATA
mojo_arrow_sys-0.1.20.dist-info/licenses/LICENSE
