Metadata-Version: 2.4
Name: mojo_arrow_sys
Version: 0.1.20
Summary: Python C extension for accessing Arrow C streams from Mojo
Author-email: Marius Seritan <pypi@seritan.net>
License: MIT License
Project-URL: Homepage, https://github.com/winding-lines/mojo_arrow_sys
Project-URL: BugTracker, https://github.com/winding-lines/mojo_arrow_sys/issues
Classifier: Programming Language :: Python :: 3
Classifier: Programming Language :: Python :: 3.10
Classifier: Programming Language :: Python :: 3.11
Classifier: Programming Language :: Python :: 3.12
Classifier: Operating System :: POSIX :: Linux
Classifier: Operating System :: MacOS :: MacOS X
Classifier: Development Status :: 3 - Alpha
Classifier: Intended Audience :: Developers
Classifier: Topic :: Software Development :: Libraries :: Python Modules
Requires-Python: >=3.10
License-File: LICENSE
Requires-Dist: ruff>=0.11.3
Dynamic: license-file
